requirements.txt
comoda/APPNAME
comoda/VERSION
comoda/__init__.py
comoda/yaml.py
comoda-0.4.2.dist-info/METADATA
comoda-0.4.2.dist-info/WHEEL
comoda-0.4.2.dist-info/top_level.txt
comoda-0.4.2.dist-info/zip-safe
comoda-0.4.2.dist-info/RECORD
